k8stop/LICENSE
k8stop/__init__.py
k8s_top-0.0.1.dev20210130014949.dist-info/METADATA
k8s_top-0.0.1.dev20210130014949.dist-info/WHEEL
k8s_top-0.0.1.dev20210130014949.dist-info/namespace_packages.txt
k8s_top-0.0.1.dev20210130014949.dist-info/top_level.txt
k8s_top-0.0.1.dev20210130014949.dist-info/zip-safe
k8s_top-0.0.1.dev20210130014949.dist-info/RECORD
